[
    {
        "key": "dbln",
        "value": "%7B%22100090546561163%22%3A%22QJ5o8Hnu%22%7D",
        "domain": "facebook.com",
        "path": "/login/device-based/",
        "hostOnly": false,
        "creation": "2025-08-11T07:24:36.148Z",
        "lastAccessed": "2025-08-11T07:24:36.149Z"
    },
    {
        "key": "datr",
        "value": "yffvZ5LiDPUU8Ewe13PM6sfm",
        "domain": "facebook.com",
        "path": "/",
        "hostOnly": false,
        "creation": "2025-08-11T07:24:36.149Z",
        "lastAccessed": "2025-08-11T07:24:36.149Z"
    },
    {
        "key": "sb",
        "value": "yffvZ64OPJYuLuCyW8XOX7Ad",
        "domain": "facebook.com",
        "path": "/",
        "hostOnly": false,
        "creation": "2025-08-11T07:24:36.149Z",
        "lastAccessed": "2025-08-11T07:24:36.149Z"
    },
    {
        "key": "ps_l",
        "value": "1",
        "domain": "facebook.com",
        "path": "/",
        "hostOnly": false,
        "creation": "2025-08-11T07:24:36.149Z",
        "lastAccessed": "2025-08-11T07:24:36.149Z"
    },
    {
        "key": "ps_n",
        "value": "1",
        "domain": "facebook.com",
        "path": "/",
        "hostOnly": false,
        "creation": "2025-08-11T07:24:36.149Z",
        "lastAccessed": "2025-08-11T07:24:36.149Z"
    },
    {
        "key": "dpr",
        "value": "2.549999952316284",
        "domain": "facebook.com",
        "path": "/",
        "hostOnly": false,
        "creation": "2025-08-11T07:24:36.150Z",
        "lastAccessed": "2025-08-11T07:24:36.150Z"
    },
    {
        "key": "locale",
        "value": "en_GB",
        "domain": "facebook.com",
        "path": "/",
        "hostOnly": false,
        "creation": "2025-08-11T07:24:36.150Z",
        "lastAccessed": "2025-08-11T07:24:36.150Z"
    },
    {
        "key": "wd",
        "value": "980x1848",
        "domain": "facebook.com",
        "path": "/",
        "hostOnly": false,
        "creation": "2025-08-11T07:24:36.150Z",
        "lastAccessed": "2025-08-11T07:24:36.150Z"
    },
    {
        "key": "c_user",
        "value": "61579056942348",
        "domain": "facebook.com",
        "path": "/",
        "hostOnly": false,
        "creation": "2025-08-11T07:24:36.150Z",
        "lastAccessed": "2025-08-11T07:24:36.150Z"
    },
    {
        "key": "fr",
        "value": "1gFSirPELAQfoW8wK.AWcGUkpI-oir5tlVySwYcJ2wQRUMKrUQEOvWK0hH4hy_vrc0wfE.BomZN_..AAA.0.0.BomZqQ.AWfPVuGaZigWu-RQldt5EwKB5Nk",
        "domain": "facebook.com",
        "path": "/",
        "hostOnly": false,
        "creation": "2025-08-11T07:24:36.150Z",
        "lastAccessed": "2025-08-11T07:24:36.150Z"
    },
    {
        "key": "xs",
        "value": "35%3AQ469YC7Z2uwjHg%3A2%3A1754897041%3A-1%3A-1",
        "domain": "facebook.com",
        "path": "/",
        "hostOnly": false,
        "creation": "2025-08-11T07:24:36.150Z",
        "lastAccessed": "2025-08-11T07:24:36.150Z"
    },
    {
        "key": "presence",
        "value": "C%7B%22t3%22%3A%5B%5D%2C%22utc3%22%3A1754897046620%2C%22v%22%3A1%7D",
        "domain": "facebook.com",
        "path": "/",
        "hostOnly": false,
        "creation": "2025-08-11T07:24:36.150Z",
        "lastAccessed": "2025-08-11T07:24:36.150Z"
    }
]
